{
  "schema_type": "object",
  "ree_version": "0.1.0",
  "name": "prev_quarter",
  "path": "packages/ree_date/package/ree_date/functions/prev_quarter.rb",
  "mount_as": "fn",
  "class": "ReeDate::PrevQuarter",
  "factory": null,
  "methods": [
    {
      "doc": "Short-hand for <tt>quarters_ago(1)</tt>.",
      "throws": [

      ],
      "return": "Date",
      "args": [
        {
          "arg": "date",
          "type": "Nilor[Date]"
        }
      ]
    }
  ],
  "links": [
    {
      "target": "advance",
      "package_name": "ree_date",
      "as": "advance",
      "imports": [

      ]
    },
    {
      "target": "today",
      "package_name": "ree_date",
      "as": "today",
      "imports": [

      ]
    }
  ]
}